src/__init__.py
src/auxn_agent/__init__.py
src/auxn_agent/main.py
src/config.py
src/database/__init__.py
src/database/crud.py
src/database/database.py
src/database/models.py
src/models/__init__.py
src/models/listing.py
src/models/models.py
src/scraper/__init__.py
src/scraper/playwright_scraper.py
src/scraper/scraper_manager.py
src/utils/__init__.py
src/utils/logger.py
auxn_agent-0.2.0.dist-info/METADATA
auxn_agent-0.2.0.dist-info/WHEEL
auxn_agent-0.2.0.dist-info/entry_points.txt
auxn_agent-0.2.0.dist-info/RECORD
