Metadata-Version: 2.3
Name: auxn-agent
Version: 0.2.0
Summary: A web scraping and data extraction tool.
License: MIT
Keywords: web scraping,data extraction,automation
Author: Your Name
Author-email: your.email@example.com
Requires-Python: >=3.10,<4.0
Classifier: Development Status :: 3 - Alpha
Classifier: Intended Audience :: Developers
Classifier: License :: OSI Approved :: MIT License
Classifier: Programming Language :: Python :: 3
Classifier: Programming Language :: Python :: 3.10
Classifier: Programming Language :: Python :: 3.11
Classifier: Programming Language :: Python :: 3.12
Classifier: Programming Language :: Python :: 3.13
Requires-Dist: SQLAlchemy-Utils (>=0.41.1)
Requires-Dist: aiofiles (>=23.2.1)
Requires-Dist: aiohttp (==3.9.3)
Requires-Dist: aiohttp-retry (==2.8.3)
Requires-Dist: loguru (>=0.7.2)
Requires-Dist: playwright (>=1.40.0)
Requires-Dist: pydantic (>=2.5.2)
Requires-Dist: pydantic-settings (>=2.0.0)
Requires-Dist: pytest (==7.4.3)
Requires-Dist: pytest-aiohttp (==1.0.5)
Requires-Dist: pytest-asyncio (==0.21.1)
Requires-Dist: pytest-timeout (==2.2.0)
Requires-Dist: python-dotenv (>=1.0.0)
Requires-Dist: sqlalchemy (>=2.0.23)
Requires-Dist: typing-extensions (>=4.9.0)
Project-URL: Bug Tracker, https://github.com/your-username/auxn-agent/issues
Project-URL: Documentation, https://github.com/your-username/auxn-agent/wiki
Project-URL: Repository, https://github.com/your-username/auxn-agent
